{
  "version": 1,
  "programId": "Ab1nTbMuFjcfoRJWWAdxPAVotYz2kzPxS18Yzie2iiQt",
  "instructionName": "deposit",
  "discriminator": [
    242,
    35,
    198,
    137,
    82,
    225,
    242,
    182
  ],
  "params": [
    {
      "name": "pool_id",
      "paramType": "u64",
      "constraintType": "none",
      "constraintValue": 0
    },
    {
      "name": "amount",
      "paramType": "u64",
      "constraintType": "none",
      "constraintValue": 0
    }
  ],
  "accounts": [
    {
      "name": "user",
      "source": "param",
      "writable": true,
      "isSigner": true,
      "sourceData": null
    },
    {
      "name": "pool",
      "source": "pda",
      "writable": true,
      "isSigner": false,
      "sourceData": {
        "seedCount": 2,
        "seedStart": 0
      }
    },
    {
      "name": "pool_authority",
      "source": "pda",
      "writable": false,
      "isSigner": false,
      "sourceData": {
        "seedCount": 2,
        "seedStart": 2
      }
    },
    {
      "name": "deposit_vault",
      "source": "pda",
      "writable": true,
      "isSigner": false,
      "sourceData": {
        "program": "ATokenGPvbdGVxr1b2hvZbsiqW5xWH25efTNsLJA8knL",
        "seedCount": 3,
        "seedStart": 4
      }
    },
    {
      "name": "user_deposit_ata",
      "source": "pda",
      "writable": true,
      "isSigner": false,
      "sourceData": {
        "program": "ATokenGPvbdGVxr1b2hvZbsiqW5xWH25efTNsLJA8knL",
        "seedCount": 3,
        "seedStart": 7
      }
    },
    {
      "name": "deposit_mint",
      "source": "param",
      "writable": false,
      "isSigner": false,
      "sourceData": null
    },
    {
      "name": "depositor_info",
      "source": "pda",
      "writable": true,
      "isSigner": false,
      "sourceData": {
        "seedCount": 3,
        "seedStart": 10
      }
    },
    {
      "name": "system_program",
      "source": "static",
      "writable": false,
      "isSigner": false,
      "sourceData": "11111111111111111111111111111111"
    },
    {
      "name": "token_program",
      "source": "param",
      "writable": false,
      "isSigner": false,
      "sourceData": null
    },
    {
      "name": "associated_token_program",
      "source": "static",
      "writable": false,
      "isSigner": false,
      "sourceData": "ATokenGPvbdGVxr1b2hvZbsiqW5xWH25efTNsLJA8knL"
    }
  ],
  "dataSegments": [
    {
      "segmentType": "literal",
      "data": [
        242,
        35,
        198,
        137,
        82,
        225,
        242,
        182
      ],
      "paramIndex": null
    },
    {
      "segmentType": "param",
      "data": null,
      "paramIndex": 0
    },
    {
      "segmentType": "param",
      "data": null,
      "paramIndex": 1
    }
  ],
  "seeds": [
    {
      "seedType": "literal",
      "value": [
        112,
        111,
        111,
        108
      ],
      "paramIndex": null,
      "accountIndex": null
    },
    {
      "seedType": "param",
      "value": null,
      "paramIndex": 0,
      "accountIndex": null
    },
    {
      "seedType": "literal",
      "value": [
        112,
        111,
        111,
        108,
        45,
        97,
        117,
        116,
        104,
        111,
        114,
        105,
        116,
        121
      ],
      "paramIndex": null,
      "accountIndex": null
    },
    {
      "seedType": "param",
      "value": null,
      "paramIndex": 0,
      "accountIndex": null
    },
    {
      "seedType": "account",
      "value": null,
      "paramIndex": null,
      "accountIndex": 2
    },
    {
      "seedType": "account",
      "value": null,
      "paramIndex": null,
      "accountIndex": 8
    },
    {
      "seedType": "account",
      "value": "pool.deposit_mint",
      "paramIndex": null,
      "accountIndex": 1
    },
    {
      "seedType": "account",
      "value": null,
      "paramIndex": null,
      "accountIndex": 0
    },
    {
      "seedType": "account",
      "value": null,
      "paramIndex": null,
      "accountIndex": 8
    },
    {
      "seedType": "account",
      "value": "pool.deposit_mint",
      "paramIndex": null,
      "accountIndex": 1
    },
    {
      "seedType": "literal",
      "value": [
        100,
        101,
        112,
        111,
        115,
        105,
        116,
        111,
        114,
        45,
        105,
        110,
        102,
        111
      ],
      "paramIndex": null,
      "accountIndex": null
    },
    {
      "seedType": "account",
      "value": null,
      "paramIndex": null,
      "accountIndex": 0
    },
    {
      "seedType": "account",
      "value": "pool.id",
      "paramIndex": null,
      "accountIndex": 1
    }
  ],
  "template": "deposit: {pool_id}, {amount}",
  "riskLevel": "HIGH",
  "timelockSeconds": 3600,
  "verification": {
    "tier": 2,
    "programName": null,
    "verified": null
  }
}